{
    "version": "0.43.99",
    "architecture": {
        "64bit": {
            "url": "https://github.com/Infisical/cli/releases/download/v0.43.99/cli_0.43.99_windows_amd64.zip",
            "bin": [
                "infisical.exe"
            ],
            "hash": "39b077e34016451b529b8aaa440871c561460f11706b5ce45f3ddacaa0469eee"
        },
        "arm64": {
            "url": "https://github.com/Infisical/cli/releases/download/v0.43.99/cli_0.43.99_windows_arm64.zip",
            "bin": [
                "infisical.exe"
            ],
            "hash": "2bfa4f5df152243d28c7b65141c1deb39af117955bca140a03ad06babca94c6f"
        }
    },
    "homepage": "https://infisical.com",
    "license": "MIT",
    "description": "The official Infisical CLI"
}