{
    "version": "0.2.7",
    "architecture": {
        "32bit": {
            "url": "https://github.com/Infisical/infisical/releases/download/v0.2.7/infisical_0.2.7_windows_386.tar.gz",
            "bin": [
                "infisical.exe"
            ],
            "hash": "e988137981038bd35cfebd4ba302b08819d14589dad743b2d586290e28a42399"
        },
        "64bit": {
            "url": "https://github.com/Infisical/infisical/releases/download/v0.2.7/infisical_0.2.7_windows_amd64.tar.gz",
            "bin": [
                "infisical.exe"
            ],
            "hash": "109edac242bcd8e8c99e42dd587498020c28ed2542040532bd00d528d5ec228b"
        }
    },
    "homepage": "https://infisical.com",
    "license": "Apache-2.0",
    "description": "The official Infisical CLI"
}